mldatafind/__init__.py
mldatafind/fetch.py
mldatafind/segments.py
mldatafind/authenticate/__init__.py
mldatafind/authenticate/scitoken.py
mldatafind/authenticate/x509.py
mldatafind/law/base.py
mldatafind/law/config.py
mldatafind/law/parameters.py
mldatafind/law/targets.py
mldatafind/law/tasks/__init__.py
mldatafind/law/tasks/fetch.py
mldatafind/law/tasks/segments.py
mldatafind/law/tasks/condor/__init__.py
mldatafind/law/tasks/condor/base.py
mldatafind/law/tasks/condor/workflows.py
mldatafind-0.1.8.dist-info/METADATA
mldatafind-0.1.8.dist-info/WHEEL
mldatafind-0.1.8.dist-info/licenses/LICENSE
mldatafind-0.1.8.dist-info/RECORD
