Metadata-Version: 2.4
Name: mldatafind
Version: 0.1.8
Summary: Luigi/Law Tasks for streamlining gravitational wave data discovery
Author-email: Ethan Marx <emarx@mit.edu>
License-Expression: MIT
License-File: LICENSE
Requires-Python: <3.13,>=3.10
Requires-Dist: boto3<2,>=1.34.4
Requires-Dist: cloudpathlib<0.19,>=0.18.1
Requires-Dist: gwpy>=3.0.12
Requires-Dist: htgettoken>=2.2
Requires-Dist: law<0.2,>=0.1.19
Requires-Dist: luigi<4,>=3.5.1
